jztools/__init__.py
jztools/algos.py
jztools/autonamed_pattern.py
jztools/colorama.py
jztools/contextlib.py
jztools/datetime.py
jztools/datetime64.py
jztools/filelock.py
jztools/files.py
jztools/freezegun.py
jztools/general.py
jztools/gunicorn.py
jztools/humanize.py
jztools/json.py
jztools/logging.py
jztools/mplib.py
jztools/numpy.py
jztools/os.py
jztools/profile.py
jztools/profiling.py
jztools/py.py
jztools/reference_sequence.py
jztools/reference_sequence2.py
jztools/reference_sequence_v0.py
jztools/rentemp.py
jztools/shared_memory.py
jztools/slice_sequence.py
jztools/socket.py
jztools/sphinx.py
jztools/timer.py
jztools/validation.py
jztools/nnets/__init__.py
jztools/nnets/numtor.py
jztools/object_recorder/__init__.py
jztools/object_recorder/_testing_utils.py
jztools/object_recorder/call_unordered.py
jztools/object_recorder/example.py
jztools/object_recorder/global_time.py
jztools/object_recorder/object_recorder.py
jztools/object_recorder/rec_obj_factory.py
jztools/object_recorder/rec_obj_factory__call_unordered.py
jztools/object_recorder/rec_obj_factory__defs.py
jztools/object_recorder/record_instances.py
jztools/object_recorder/recorded_attributes.py
jztools/object_recorder/recording_switch_utils.py
jztools/object_recorder/replicate.py
jztools/object_recorder/utils.py
jztools/object_recorder/freeze_call_times/__init__.py
jztools/object_recorder/freeze_call_times/freeze_call_times.py
jztools/object_recorder/freeze_call_times/stack.py
jztools/pacers/__init__.py
jztools/pacers/pacers.py
jztools/parallelization/__init__.py
jztools/parallelization/_base.py
jztools/parallelization/_outsourced_iterable_base.py
jztools/parallelization/mock.py
jztools/parallelization/outsourced_callable_base.py
jztools/parallelization/selector.py
jztools/parallelization/utils.py
jztools/parallelization/multiprocessing/__init__.py
jztools/parallelization/multiprocessing/handlers.py
jztools/parallelization/multiprocessing/outsourced_iterable.py
jztools-0.1.6.dist-info/LICENSE
jztools-0.1.6.dist-info/METADATA
jztools-0.1.6.dist-info/WHEEL
jztools-0.1.6.dist-info/top_level.txt
jztools-0.1.6.dist-info/RECORD
