Metadata-Version: 2.1
Name: jztools
Version: 0.1.6
Summary: General python utilies
Home-page: https://github.com/zepedaj/jztools
Author: Joaquin Zepeda
License-File: LICENSE
Requires-Dist: pygments
Requires-Dist: numpy
Requires-Dist: climax
Requires-Dist: tqdm
Requires-Dist: coloredlogs
Requires-Dist: SQLAlchemy
Requires-Dist: xerializer
Requires-Dist: plotly
Requires-Dist: freezegun
Requires-Dist: torch
